odoo8_addon_hr_timesheet_task-8.0.0.3.0-py2.7-nspkg.pth
odoo8_addon_hr_timesheet_task-8.0.0.3.0.dist-info/top_level.txt
odoo8_addon_hr_timesheet_task-8.0.0.3.0.dist-info/WHEEL
odoo8_addon_hr_timesheet_task-8.0.0.3.0.dist-info/RECORD
odoo8_addon_hr_timesheet_task-8.0.0.3.0.dist-info/metadata.json
odoo8_addon_hr_timesheet_task-8.0.0.3.0.dist-info/DESCRIPTION.rst
odoo8_addon_hr_timesheet_task-8.0.0.3.0.dist-info/METADATA
odoo8_addon_hr_timesheet_task-8.0.0.3.0.dist-info/namespace_packages.txt
odoo_addons/hr_timesheet_task/__openerp__.py
odoo_addons/hr_timesheet_task/hr_analytic_timesheet_view.xml
odoo_addons/hr_timesheet_task/hr_timesheet_task.xml
odoo_addons/hr_timesheet_task/__init__.py
odoo_addons/hr_timesheet_task/hr_timesheet_sheet_view.xml
odoo_addons/hr_timesheet_task/i18n/fr.po
odoo_addons/hr_timesheet_task/static/description/icon.png
odoo_addons/hr_timesheet_task/static/src/js/timesheet.js
odoo_addons/hr_timesheet_task/static/src/css/timesheet.css
odoo_addons/hr_timesheet_task/static/src/xml/timesheet.xml
